pydrycode/__init__.py
pydrycode/attrtools.py
pydrycode/cachetools.py
pydrycode/callables.py
pydrycode/dict.py
pydrycode/methodtools.py
pydrycode/numpytools.py
pydrycode/numtools.py
pydrycode/rangetools.py
pydrycode-0.0.2.dist-info/METADATA
pydrycode-0.0.2.dist-info/WHEEL
pydrycode-0.0.2.dist-info/licenses/LICENSE
pydrycode-0.0.2.dist-info/RECORD
