Metadata-Version: 2.3
Name: pydrycode
Version: 0.0.2
Summary: A simple package with utilities for python
Project-URL: Homepage, https://github.com/Darix001/pydrycode.git
Project-URL: Issues, https://github.com/Darix001/pydrycode/issues
Author-email: Dariel Enmanuel Buret Rivera <darielburetrivera@gmail.com>
License-File: LICENSE
Classifier: License :: OSI Approved :: MIT License
Classifier: Operating System :: OS Independent
Classifier: Programming Language :: Python :: 3
Requires-Python: >=3.12
